visorRobot/__init__.py
visorRobot/visor.py
visorRobot_sample_10-0.0.1.dist-info/METADATA
visorRobot_sample_10-0.0.1.dist-info/WHEEL
visorRobot_sample_10-0.0.1.dist-info/top_level.txt
visorRobot_sample_10-0.0.1.dist-info/RECORD
